ArtNetRouter/__init__.py
ArtNetRouter/cli_entry_points.py
ArtNetRouter/core.py
ArtNetRouter-1.1.1.dist-info/METADATA
ArtNetRouter-1.1.1.dist-info/WHEEL
ArtNetRouter-1.1.1.dist-info/entry_points.txt
ArtNetRouter-1.1.1.dist-info/top_level.txt
ArtNetRouter-1.1.1.dist-info/RECORD
