Metadata-Version: 2.1
Name: ArtNetRouter
Version: 1.1.1
Summary: ArtNet router
Home-page: UNKNOWN
Author: shinaji
Author-email: shina.synergy@gmail.com
License: MIT
Platform: UNKNOWN
Classifier: Intended Audience :: Developers
Classifier: Development Status :: 4 - Beta
Classifier: Programming Language :: Python :: 3.6
Classifier: Programming Language :: Python :: 3.7
Classifier: Operating System :: OS Independent
Classifier: Topic :: Software Development
